klein_util/__init__.py
klein_util/debug.py
klein_util/dict.py
klein_util/lists.py
klein_util/mime.py
klein_util/notifications.py
klein_util-1.0.8.dist-info/LICENSE.txt
klein_util-1.0.8.dist-info/METADATA
klein_util-1.0.8.dist-info/WHEEL
klein_util-1.0.8.dist-info/top_level.txt
klein_util-1.0.8.dist-info/zip-safe
klein_util-1.0.8.dist-info/RECORD
