Metadata-Version: 2.1
Name: klein-util
Version: 1.0.8
Summary: Utility Functions & Classes
Home-page: https://github.com/mdcatapult/py-util
Author: Medicines Discovery Catapult
Author-email: SoftwareEngineering@md.catapult.org.uk
License: Apache V2
Platform: UNKNOWN
License-File: LICENSE.txt
Requires-Dist: klein-config
Requires-Dist: boto3 (<2,>=1.23.10)
